LICENSE
MANIFEST.in
README
setup.cfg
setup.py
src/_build.py
src/monotone/__init__.py
src/monotone/_api.py
src/monotone/_version.py
src/monotone.egg-info/PKG-INFO
src/monotone.egg-info/SOURCES.txt
src/monotone.egg-info/dependency_links.txt
src/monotone.egg-info/requires.txt
src/monotone.egg-info/top_level.txt
test/test_monotone.py