Metadata-Version: 1.1
Name: monotone
Version: 17.3.2
Summary: 
